foghorn/__init__.py
foghorn/app.py
foghorn/main.py
foghorn/recursive_resolver.py
foghorn/stats.py
foghorn/config/__init__.py
foghorn/config/config_parser.py
foghorn/config/config_schema.py
foghorn/config/logging_config.py
foghorn/dnssec/dnssec_validate.py
foghorn/dnssec/trust_anchors.py
foghorn/html/favicon.ico
foghorn/html/index.html
foghorn/html/logo.png
foghorn/html/styles.css
foghorn/html/transparent-logo.png
foghorn/html/transparent-white-logo.png
foghorn/plugins/__init__.py
foghorn/plugins/cache/__init__.py
foghorn/plugins/cache/base.py
foghorn/plugins/cache/in_memory_ttl.py
foghorn/plugins/cache/memcached_cache.py
foghorn/plugins/cache/mongodb_cache.py
foghorn/plugins/cache/none.py
foghorn/plugins/cache/redis_cache.py
foghorn/plugins/cache/registry.py
foghorn/plugins/cache/sqlite_cache.py
foghorn/plugins/cache/backends/foghorn_ttl.py
foghorn/plugins/cache/backends/sqlite_ttl.py
foghorn/plugins/querylog/__init__.py
foghorn/plugins/querylog/base.py
foghorn/plugins/querylog/influxdb.py
foghorn/plugins/querylog/json_logging.py
foghorn/plugins/querylog/mongodb.py
foghorn/plugins/querylog/mqtt_logging.py
foghorn/plugins/querylog/mysql_mariadb.py
foghorn/plugins/querylog/postgresql.py
foghorn/plugins/querylog/registry.py
foghorn/plugins/querylog/sqlite.py
foghorn/plugins/resolve/__init__.py
foghorn/plugins/resolve/access_control.py
foghorn/plugins/resolve/base.py
foghorn/plugins/resolve/docker_hosts.py
foghorn/plugins/resolve/etc_hosts.py
foghorn/plugins/resolve/file_downloader.py
foghorn/plugins/resolve/filter.py
foghorn/plugins/resolve/flaky_server.py
foghorn/plugins/resolve/mdns.py
foghorn/plugins/resolve/rate_limit.py
foghorn/plugins/resolve/registry.py
foghorn/plugins/resolve/upstream_router.py
foghorn/plugins/resolve/zone_records.py
foghorn/plugins/resolve/examples/dns_prefetch.py
foghorn/plugins/resolve/examples/examples.py
foghorn/plugins/resolve/examples/file_over_dns.py
foghorn/plugins/resolve/examples/finger.py
foghorn-0.6.1.dist-info/licenses/LICENSE.txt
foghorn-0.6.1.dist-info/METADATA
foghorn-0.6.1.dist-info/WHEEL
foghorn-0.6.1.dist-info/entry_points.txt
foghorn-0.6.1.dist-info/top_level.txt
foghorn-0.6.1.dist-info/RECORD
