Metadata-Version: 2.4
Name: Foghorn
Version: 0.6.1
Summary: Foghorn is a fast, pluggable DNS server that caches, filters, routes, and bends DNS to your will. Up- and down-stream UDP, TCP, DoT, and DoH. DNSEC. Because DNS should do what you want.
Author-email: Zack Allison <zack@zackallison.com>
License: MIT License
Requires-Python: >=3.11
License-File: LICENSE.txt
Requires-Dist: PyYAML>=6.0.1
Requires-Dist: cachetools
Requires-Dist: cryptography
Requires-Dist: dnslib>=0.9.24
Requires-Dist: dnspython>=2.6.1
Requires-Dist: docker>=7.0.0
Requires-Dist: fastapi>=0.111.0
Requires-Dist: httpx
Requires-Dist: jsonschema>=4.17.3
Requires-Dist: paho-mqtt
Requires-Dist: mariadb
Requires-Dist: mysql-connector-python
Requires-Dist: psutil
Requires-Dist: requests>=2.31.0
Requires-Dist: uvicorn>=0.30.0
Requires-Dist: watchdog
Requires-Dist: whois
Requires-Dist: zeroconf
Provides-Extra: dev
Requires-Dist: black; extra == "dev"
Requires-Dist: build; extra == "dev"
Requires-Dist: coverage; extra == "dev"
Requires-Dist: isort; extra == "dev"
Requires-Dist: pytest; extra == "dev"
Requires-Dist: pytest-cov; extra == "dev"
Requires-Dist: ruff; extra == "dev"
Requires-Dist: twine; extra == "dev"
Dynamic: license-file
